src/traffic_light_controller.v
module traffic_light_controller (
    input  wire clk,
    input  wire rst,
    input  wire ped_btn,
    output reg  red,
    output reg  yellow,
    output reg  green,
    output reg  ped_walk,
    output reg  [3:0] timer
);

    parameter RED_TIME    = 20;
    parameter GREEN_TIME  = 20;
    parameter YELLOW_TIME = 10;
    parameter PED_TIME    = 15;

    localparam S_RED    = 2'b00;
    localparam S_GREEN  = 2'b01;
    localparam S_YELLOW = 2'b10;
    localparam S_PED    = 2'b11;

    reg [1:0] state;
    reg [4:0] count;
    reg       ped_req;

    always @(posedge clk) begin
        if (rst) ped_req <= 0;
        else if (ped_btn) ped_req <= 1;
        else if (state == S_PED) ped_req <= 0;
    end

    always @(posedge clk) begin
        if (rst) begin
            state <= S_RED;
            count <= 0;
        end else begin
            count <= count + 1;
            case (state)
                S_RED:    if (count == RED_TIME-1)    begin count <= 0; state <= S_GREEN;  end
                S_GREEN:  if (count == GREEN_TIME-1)  begin count <= 0; state <= S_YELLOW; end
                S_YELLOW: if (count == YELLOW_TIME-1) begin count <= 0; state <= ped_req ? S_PED : S_RED; end
                S_PED:    if (count == PED_TIME-1)    begin count <= 0; state <= S_RED;    end
                default:  begin state <= S_RED; count <= 0; end
            endcase
        end
    end

    always @(*) begin
        red=0; yellow=0; green=0; ped_walk=0; timer=0;
        case (state)
            S_RED:    begin red=1;      timer = RED_TIME    - count; end
            S_GREEN:  begin green=1;    timer = GREEN_TIME  - count; end
            S_YELLOW: begin yellow=1;   timer = YELLOW_TIME - count; end
            S_PED:    begin red=1; ped_walk=1; timer = PED_TIME - count; end
        endcase
    end

endmodule

tb/tb_traffic_light.v
`timescale 1ns/1ps

module tb_traffic_light;

    reg        clk, rst, ped_btn;
    wire       red, yellow, green, ped_walk;
    wire [3:0] timer;

    traffic_light_controller #(
        .RED_TIME(10), .GREEN_TIME(10),
        .YELLOW_TIME(5), .PED_TIME(8)
    ) dut (
        .clk(clk), .rst(rst), .ped_btn(ped_btn),
        .red(red), .yellow(yellow), .green(green),
        .ped_walk(ped_walk), .timer(timer)
    );

    initial clk = 0;
    always #5 clk = ~clk;

    initial begin
        $dumpfile("sim/traffic_light.vcd");
        $dumpvars(0, tb_traffic_light);
    end

    initial begin
        $display("=== TRAFFIC LIGHT SIMULATION ===");
        rst=1; ped_btn=0;
        #30 rst=0;
        $display("Reset released - entering RED phase");
        #100;
        $display("Testing pedestrian button press");
        ped_btn=1; #10; ped_btn=0;
        #200;
        $display("Simulation complete");
        $finish;
    end

    initial begin
        $monitor("T=%0t | RED=%b YEL=%b GRN=%b PED=%b | TIMER=%0d",
                 $time, red, yellow, green, ped_walk, timer);
    end

endmodule

sim/traffic_light.vcd
$date
	Wed Apr 15 21:54:26 2026
$end
$version
	Icarus Verilog
$end
$timescale
	1ps
$end
$scope module tb_traffic_light $end
$var wire 1 ! yellow $end
$var wire 4 " timer [3:0] $end
$var wire 1 # red $end
$var wire 1 $ ped_walk $end
$var wire 1 % green $end
$var reg 1 & clk $end
$var reg 1 ' ped_btn $end
$var reg 1 ( rst $end
$scope module dut $end
$var wire 1 & clk $end
$var wire 1 ' ped_btn $end
$var wire 1 ( rst $end
$var parameter 32 ) GREEN_TIME $end
$var parameter 32 * PED_TIME $end
$var parameter 32 + RED_TIME $end
$var parameter 2 , S_GREEN $end
$var parameter 2 - S_PED $end
$var parameter 2 . S_RED $end
$var parameter 2 / S_YELLOW $end
$var parameter 32 0 YELLOW_TIME $end
$var reg 5 1 count [4:0] $end
$var reg 1 % green $end
$var reg 1 2 ped_req $end
$var reg 1 $ ped_walk $end
$var reg 1 # red $end
$var reg 2 3 state [1:0] $end
$var reg 4 4 timer [3:0] $end
$var reg 1 ! yellow $end
$upscope $end
$upscope $end
$enddefinitions $end
$comment Show the parameter values. $end
$dumpall
b101 0
b10 /
b0 .
b11 -
b1 ,
b1010 +
b1000 *
b1010 )
$end
#0
$dumpvars
bx 4
bx 3
x2
bx 1
1(
0'
0&
x%
x$
x#
bx "
x!
$end
#5000
b1010 "
b1010 4
0$
0%
0!
1#
02
b0 1
b0 3
1&
#10000
0&
#15000
1&
#20000
0&
#25000
1&
#30000
0&
0(
#35000
b1001 "
b1001 4
1#
b1 1
1&
#40000
0&
#45000
b1000 "
b1000 4
1#
b10 1
1&
#50000
0&
#55000
b111 "
b111 4
1#
b11 1
1&
#60000
0&
#65000
b110 "
b110 4
1#
b100 1
1&
#70000
0&
#75000
b101 "
b101 4
1#
b101 1
1&
#80000
0&
#85000
b100 "
b100 4
1#
b110 1
1&
#90000
0&
#95000
b11 "
b11 4
1#
b111 1
1&
#100000
0&
#105000
b10 "
b10 4
1#
b1000 1
1&
#110000
0&
#115000
b1 "
b1 4
1#
b1001 1
1&
#120000
0&
#125000
1%
b1010 "
b1010 4
0#
b1 3
b0 1
1&
#130000
0&
1'
#135000
b1001 "
b1001 4
1%
b1 1
12
1&
#140000
0&
0'
#145000
b1000 "
b1000 4
1%
b10 1
1&
#150000
0&
#155000
b111 "
b111 4
1%
b11 1
1&
#160000
0&
#165000
b110 "
b110 4
1%
b100 1
1&
#170000
0&
#175000
b101 "
b101 4
1%
b101 1
1&
#180000
0&
#185000
b100 "
b100 4
1%
b110 1
1&
#190000
0&
#195000
b11 "
b11 4
1%
b111 1
1&
#200000
0&
#205000
b10 "
b10 4
1%
b1000 1
1&
#210000
0&
#215000
b1 "
b1 4
1%
b1001 1
1&
#220000
0&
#225000
1!
b101 "
b101 4
0%
b10 3
b0 1
1&
#230000
0&
#235000
b100 "
b100 4
1!
b1 1
1&
#240000
0&
#245000
b11 "
b11 4
1!
b10 1
1&
#250000
0&
#255000
b10 "
b10 4
1!
b11 1
1&
#260000
0&
#265000
b1 "
b1 4
1!
b100 1
1&
#270000
0&
#275000
1$
1#
b1000 "
b1000 4
0!
b11 3
b0 1
1&
#280000
0&
#285000
b111 "
b111 4
1$
1#
02
b1 1
1&
#290000
0&
#295000
b110 "
b110 4
1$
1#
b10 1
1&
#300000
0&
#305000
b101 "
b101 4
1$
1#
b11 1
1&
#310000
0&
#315000
b100 "
b100 4
1$
1#
b100 1
1&
#320000
0&
#325000
b11 "
b11 4
1$
1#
b101 1
1&
#330000
0&
#335000
b10 "
b10 4
1$
1#
b110 1
1&
